goedge/__init__.py
goedge/core.py
goedge/ge_storage.py
goedge_core_sdk_python-0.1.1.dist-info/METADATA
goedge_core_sdk_python-0.1.1.dist-info/WHEEL
goedge_core_sdk_python-0.1.1.dist-info/RECORD
