Metadata-Version: 2.3
Name: goedge-core-sdk-python
Version: 0.1.1
Summary: GoEdge Core SDK Python Wrapper
Author: zhangtc
Author-email: zhangtc@rigoiot.com
Requires-Python: >=3.8
Classifier: Programming Language :: Python :: 3
Classifier: Programming Language :: Python :: 3.8
Classifier: Programming Language :: Python :: 3.9
Classifier: Programming Language :: Python :: 3.10
Classifier: Programming Language :: Python :: 3.11
Classifier: Programming Language :: Python :: 3.12
Classifier: Programming Language :: Python :: 3.13
